escapist/__init__.py
escapist/__main__.py
escapist/__version__.py
escapist/exceptions.py
escapist/utils.py
escapist/cli/__init__.py
escapist/core/__init__.py
escapist-1.0.2.dist-info/METADATA
escapist-1.0.2.dist-info/WHEEL
escapist-1.0.2.dist-info/entry_points.txt
escapist-1.0.2.dist-info/licenses/LICENSE
escapist-1.0.2.dist-info/RECORD
