Metadata-Version: 2.4
Name: escapist
Version: 1.0.2
Summary: A lightweight tool and CLI for rendering Jinja2 templates with JSON or Python data, ideal for scripting and automation workflows.
Project-URL: Documentation, https://github.com/jd-35656/escapist#readme
Project-URL: Issues, https://github.com/jd-35656/escapist/issues
Project-URL: Source, https://github.com/jd-35656/escapist
Author-email: "Jitesh Sahani (JD)" <jitesh.sahani@outlook.com>
License-Expression: MIT
License-File: LICENSE
Keywords: automation,cli,configuration,jinja2,jinja2-renderer,json,rendering,template,templating,yaml
Classifier: Development Status :: 4 - Beta
Classifier: Programming Language :: Python
Classifier: Programming Language :: Python :: 3 :: Only
Classifier: Programming Language :: Python :: 3.10
Classifier: Programming Language :: Python :: 3.11
Classifier: Programming Language :: Python :: 3.12
Classifier: Programming Language :: Python :: 3.13
Classifier: Programming Language :: Python :: Implementation :: CPython
Classifier: Programming Language :: Python :: Implementation :: PyPy
Requires-Python: >=3.10
Requires-Dist: click>=8.3
Requires-Dist: jinja2>=3.1.6
Provides-Extra: docs
Requires-Dist: click; extra == 'docs'
Requires-Dist: jinja2; extra == 'docs'
Requires-Dist: mike; extra == 'docs'
Requires-Dist: mkdocs; extra == 'docs'
Requires-Dist: mkdocs-autorefs; extra == 'docs'
Requires-Dist: mkdocs-gen-files; extra == 'docs'
Requires-Dist: mkdocs-macros-plugin; extra == 'docs'
Requires-Dist: mkdocs-material; extra == 'docs'
Requires-Dist: mkdocstrings; extra == 'docs'
Requires-Dist: mkdocstrings-python; extra == 'docs'
Requires-Dist: pymdown-extensions; extra == 'docs'
Requires-Dist: pyyaml; extra == 'docs'
Requires-Dist: ruff; extra == 'docs'
Requires-Dist: towncrier; extra == 'docs'
Provides-Extra: tests
Requires-Dist: pytest-cov>=6.1.1; extra == 'tests'
Requires-Dist: pytest>=8.3.5; extra == 'tests'
Provides-Extra: types
